dplex/__init__.py
dplex/dp_filters.py
dplex/dp_repo.py
dplex/dp_service.py
dplex/internal/filter_applier.py
dplex/internal/filters.py
dplex/internal/query_builder.py
dplex/internal/sort.py
dplex/internal/types.py
dplex-0.1.9.dist-info/licenses/LICENSE
dplex-0.1.9.dist-info/METADATA
dplex-0.1.9.dist-info/WHEEL
dplex-0.1.9.dist-info/RECORD
