Metadata-Version: 2.4
Name: dplex
Version: 0.1.9
Summary: 
License-Expression: MIT
License-File: LICENSE
Author: Igor Chesnokov
Author-email: front-gold@mail.ru
Requires-Python: >=3.9
Classifier: Programming Language :: Python :: 3
Classifier: Programming Language :: Python :: 3.9
Classifier: Programming Language :: Python :: 3.10
Classifier: Programming Language :: Python :: 3.11
Classifier: Programming Language :: Python :: 3.12
Classifier: Programming Language :: Python :: 3.13
Classifier: Programming Language :: Python :: 3.14
Requires-Dist: pydantic (>=2.11.9,<3.0.0)
Requires-Dist: sqlalchemy (>=2.0.43,<3.0.0)
